{"cameraMode":{"drawMode":0,"name":"Shaded","section":"Shading Mode"},"sceneLighting":true,"audioPlay":false,"sceneViewState":{"showFog":true,"showMaterialUpdate":false,"showSkybox":true,"showFlares":true,"showImageEffects":true,"showParticleSystems":true},"in2DMode":false,"pivot":{"x":0.7421848773956299,"y":3.1337087154388429,"z":10.436675071716309},"rotation":{"x":0.10417783260345459,"y":0.03381046652793884,"z":-0.004031464457511902,"w":0.9943631291389465},"size":27.14449691772461,"orthographic":false}