{"cameraMode":{"drawMode":0,"name":"Shaded","section":"Shading Mode"},"sceneLighting":true,"audioPlay":false,"sceneViewState":{"showFog":true,"showMaterialUpdate":false,"showSkybox":true,"showFlares":true,"showImageEffects":true,"showParticleSystems":true},"in2DMode":false,"pivot":{"x":0.9564427137374878,"y":-0.32033371925354006,"z":-2.674203872680664},"rotation":{"x":0.060863833874464038,"y":-0.007162838708609343,"z":0.0006002257578074932,"w":0.9982166886329651},"size":8.49686050415039,"orthographic":false}